rush/__init__.py
rush/exceptions.py
rush/limit_data.py
rush/py.typed
rush/quota.py
rush/result.py
rush/throttle.py
rush/contrib/__init__.py
rush/contrib/decorator.py
rush/limiters/__init__.py
rush/limiters/base.py
rush/limiters/gcra.py
rush/limiters/periodic.py
rush/limiters/redis_gcra.py
rush/stores/__init__.py
rush/stores/base.py
rush/stores/dictionary.py
rush/stores/redis.py
rush-2021.4.0.dist-info/LICENSE
rush-2021.4.0.dist-info/METADATA
rush-2021.4.0.dist-info/WHEEL
rush-2021.4.0.dist-info/top_level.txt
rush-2021.4.0.dist-info/RECORD
