Metadata-Version: 2.1
Name: rush
Version: 2021.4.0
Summary: A library for throttling algorithms
Home-page: https://github.com/sigmavirus24/rush
Author: Ian Stapleton Cordasco
Author-email: graffatcolmingov@gmail.com
License: MIT
Keywords: throttles throttle algorithm gcra redis
Platform: UNKNOWN
Classifier: Development Status :: 5 - Production/Stable
Classifier: Environment :: Console
Classifier: Intended Audience :: Developers
Classifier: License :: OSI Approved :: MIT License
Classifier: Programming Language :: Python
Classifier: Programming Language :: Python :: 3.6
Classifier: Programming Language :: Python :: 3.7
Requires-Python: >=3.6
Provides-Extra: redis
